[
    {
        "type1":"手机",
        "type2":"充值"    
    },
    {
        "type1":"相机",
        "type2":"智能数码"
    },
    {
        "type1":"电脑",
        "type2":"办公设备"
    },
    {
        "type1":"电视",
        "type2":"影音",
        "type3":"智能"
    },{
        "type1":"空调",
        "type2":"冰箱",
        "type3":"洗衣机"
    },{
        "type1":"厨房卫浴",
        "type2":"生活电器",
        "type3":"环境"
    },{
        "type1":"家具",
        "type2":"建材",
        "type3":"欧洲厨房"
    },{
        "type1":"家具家纺",
        "type2":"家居家装"
    },{
        "type1":"食用酒水"
    },{
        "type1":"母婴玩具"
    },{
        "type1":"美妆个护"
    },{
        "type1":"服饰鞋帽",
        "type2":"箱包奢品"
    },{
        "type1":"运动户外",
        "type2":"钟表首饰"
    },{
        "type1":"汽车整车",
        "type2":"汽车用品"
    },{
        "type1":"国美管家"
    }
]